{
    "@class": "com.kony.gen.viz.model.component.KVizImage2",
    "DNDConfig": null,
    "_base64_": null,
    "_height_": {
        "type": "string",
        "value": "30dp"
    },
    "_left_": {
        "type": "string",
        "value": "229dp"
    },
    "_margin_": [
        0,
        0,
        0,
        0
    ],
    "_padding_": [
        0,
        0,
        0,
        0
    ],
    "_skin_": "se7c23e3ff1a47c4a81fcf01c33ce421",
    "_src_": "icon_footer_insta.png",
    "_top_": {
        "type": "string",
        "value": "0dp"
    },
    "_width_": {
        "type": "string",
        "value": "30dp"
    },
    "canUpdateUI": true,
    "containerweight": 100,
    "id": "IconInsta",
    "imagescalemode": 1,
    "info": null,
    "iscustomlayout": false,
    "isvisible": true,
    "kuid": "u83c44552b8c4d24b65fe16beeccbd82",
    "name": "kony.ui.Image2",
    "parent": "BoxListIconSocial",
    "pf": "userwidgetmodel",
    "retaincontentalignment": false,
    "retainflexpositionproperties": false,
    "srcType": 1,
    "wType": "Image",
    "widgetalignment": 5,
    "zindex": 1
}