{
    "DNDConfig": null,
    "_height_": {
        "type": "string",
        "value": "94%"
    },
    "_left_": {
        "type": "string",
        "value": "3%"
    },
    "_margin_": [
        0,
        0,
        0,
        0
    ],
    "_orientation_": 6,
    "_padding_": [
        0,
        0,
        0,
        0
    ],
    "_percent_": true,
    "_skin_": "sa75e888d8a3456585a893417657d400",
    "_top_": {
        "type": "string",
        "value": "3%"
    },
    "_width_": {
        "type": "string",
        "value": "94%"
    },
    "allboxes": [],
    "autogrowmode": 0,
    "canUpdateUI": true,
    "children": [
        "Image0dc6020290fcf41",
        "FlexContainerleft",
        "FlexContaineright",
        "Button0eb5f155372f14b",
        "Label0a29063fbc44c4c",
        "btn1",
        "btn2",
        "btn3",
        "btn4",
        "bnt5",
        "btn6",
        "Label0ib05ea7b27d845"
    ],
    "clipbounds": false,
    "containerweight": 100,
    "enablescrolling": true,
    "id": "FlexContainer0ec0403d4e6fd41",
    "info": null,
    "iscustomlayout": false,
    "isvisible": true,
    "kuid": "c9a08ba2fb994484b22be08c06e23ee3",
    "layouttype": 2,
    "name": "kony.ui.FlexContainer",
    "parent": "FlexContainer2",
    "pf": "Dashboard",
    "retaincontentalignment": false,
    "retainflexpositionproperties": false,
    "retainflowhorizontalalignment": false,
    "snapgridsize": 10,
    "snaptogrid": true,
    "wType": "FlexContainer",
    "widgetalignment": 1,
    "zindex": 1
}